binDB/__init__.py
binDB/bindb.py
binDB/data/AD.json
binDB/data/AE.json
binDB/data/AF.json
binDB/data/AG.json
binDB/data/AI.json
binDB/data/AL.json
binDB/data/AM.json
binDB/data/AO.json
binDB/data/AR.json
binDB/data/AS.json
binDB/data/AT.json
binDB/data/AU.json
binDB/data/AW.json
binDB/data/AZ.json
binDB/data/BA.json
binDB/data/BB.json
binDB/data/BD.json
binDB/data/BE.json
binDB/data/BF.json
binDB/data/BG.json
binDB/data/BH.json
binDB/data/BI.json
binDB/data/BJ.json
binDB/data/BM.json
binDB/data/BN.json
binDB/data/BO.json
binDB/data/BQ.json
binDB/data/BR.json
binDB/data/BS.json
binDB/data/BT.json
binDB/data/BW.json
binDB/data/BY.json
binDB/data/BZ.json
binDB/data/CA.json
binDB/data/CD.json
binDB/data/CF.json
binDB/data/CG.json
binDB/data/CH.json
binDB/data/CI.json
binDB/data/CK.json
binDB/data/CL.json
binDB/data/CM.json
binDB/data/CN.json
binDB/data/CO.json
binDB/data/CR.json
binDB/data/CU.json
binDB/data/CV.json
binDB/data/CW.json
binDB/data/CY.json
binDB/data/CZ.json
binDB/data/DE.json
binDB/data/DJ.json
binDB/data/DK.json
binDB/data/DM.json
binDB/data/DO.json
binDB/data/DZ.json
binDB/data/EC.json
binDB/data/EE.json
binDB/data/EG.json
binDB/data/ER.json
binDB/data/ES.json
binDB/data/ET.json
binDB/data/FI.json
binDB/data/FJ.json
binDB/data/FK.json
binDB/data/FM.json
binDB/data/FR.json
binDB/data/GA.json
binDB/data/GB.json
binDB/data/GD.json
binDB/data/GE.json
binDB/data/GG.json
binDB/data/GH.json
binDB/data/GI.json
binDB/data/GM.json
binDB/data/GN.json
binDB/data/GQ.json
binDB/data/GR.json
binDB/data/GT.json
binDB/data/GU.json
binDB/data/GW.json
binDB/data/GY.json
binDB/data/HK.json
binDB/data/HN.json
binDB/data/HR.json
binDB/data/HT.json
binDB/data/HU.json
binDB/data/ID.json
binDB/data/IE.json
binDB/data/IL.json
binDB/data/IM.json
binDB/data/IN.json
binDB/data/IQ.json
binDB/data/IR.json
binDB/data/IS.json
binDB/data/ISOCODE2.json
binDB/data/IT.json
binDB/data/JE.json
binDB/data/JM.json
binDB/data/JO.json
binDB/data/JP.json
binDB/data/KE.json
binDB/data/KG.json
bindb-0.1.8.dist-info/licenses/LICENSE
bindb-0.1.8.dist-info/METADATA
bindb-0.1.8.dist-info/WHEEL
bindb-0.1.8.dist-info/top_level.txt
bindb-0.1.8.dist-info/RECORD
