Metadata-Version: 2.4
Name: binDB
Version: 0.1.8
Summary: A Python library for retrieving BIN (Bank Identification Number) information.
Author: islamraisul796
Author-email: islamraisul796@gmail.com
Classifier: Programming Language :: Python :: 3
Classifier: License :: OSI Approved :: MIT License
Classifier: Operating System :: OS Independent
Requires-Python: >=3.6
License-File: LICENSE
Requires-Dist: pycountry
Requires-Dist: pycountry-convert
Requires-Dist: fuzzywuzzy
Dynamic: author
Dynamic: author-email
Dynamic: classifier
Dynamic: description
Dynamic: description-content-type
Dynamic: license-file
Dynamic: requires-dist
Dynamic: requires-python
Dynamic: summary
